LICENSE.rst
py_gitignore/__init__.py
py_gitignore/py_gitignore.py
py_gitignore/template.py
py_gitignore-0.1.3.dist-info/entry_points.txt
py_gitignore-0.1.3.dist-info/LICENSE.rst
py_gitignore-0.1.3.dist-info/WHEEL
py_gitignore-0.1.3.dist-info/METADATA
py_gitignore-0.1.3.dist-info/RECORD
