Metadata-Version: 2.1
Name: py-gitignore
Version: 0.1.3
Summary: cli to add gitignore file
Home-page: https://github.com/bdista/py-gitignore
License: MIT
Author: bdista
Author-email: bdista@users.noreply.github.com
Requires-Python: >=3.9,<4.0
Classifier: License :: OSI Approved :: MIT License
Classifier: Programming Language :: Python :: 3
Classifier: Programming Language :: Python :: 3.9
Project-URL: Repository, https://github.com/bdista/py-gitignore
